quarkapi/__init__.py
quarkapi/__main__.py
quarkapi/client.py
quarkapi/console.py
quarkapi/constants.py
quarkapi/dataclass_json_encoder.py
quarkapi/entities.py
quarkapi/tcp.py
quarkapi-1.0.dist-info/LICENSE
quarkapi-1.0.dist-info/METADATA
quarkapi-1.0.dist-info/WHEEL
quarkapi-1.0.dist-info/top_level.txt
quarkapi-1.0.dist-info/RECORD
